{"metadata": {"dbt_schema_version": "https://schemas.getdbt.com/dbt/run-results/v4.json", "dbt_version": "1.2.2", "generated_at": "2022-10-15T01:42:17.881086Z", "invocation_id": "34823990-3655-474e-8e81-a72e35bca668", "env": {}}, "results": [{"status": "success", "timing": [{"name": "compile", "started_at": "2022-10-15T01:42:14.182735Z", "completed_at": "2022-10-15T01:42:14.188962Z"}, {"name": "execute", "started_at": "2022-10-15T01:42:14.190748Z", "completed_at": "2022-10-15T01:42:15.856291Z"}], "thread_id": "Thread-2", "execution_time": 2.1437783241271973, "adapter_response": {"_message": "SUCCESS 1", "code": "SUCCESS", "rows_affected": 1, "query_id": "01a7a266-0000-0a4c-0000-000026c9704d"}, "message": "SUCCESS 1", "failures": null, "unique_id": "model.my_dbt_hero.src_listings"}, {"status": "success", "timing": [{"name": "compile", "started_at": "2022-10-15T01:42:14.176462Z", "completed_at": "2022-10-15T01:42:14.190352Z"}, {"name": "execute", "started_at": "2022-10-15T01:42:14.206969Z", "completed_at": "2022-10-15T01:42:15.861630Z"}], "thread_id": "Thread-1", "execution_time": 2.164006233215332, "adapter_response": {"_message": "SUCCESS 1", "code": "SUCCESS", "rows_affected": 1, "query_id": "01a7a266-0000-0a4e-0000-000026c96049"}, "message": "SUCCESS 1", "failures": null, "unique_id": "model.my_dbt_hero.src_hosts"}, {"status": "success", "timing": [{"name": "compile", "started_at": "2022-10-15T01:42:16.327294Z", "completed_at": "2022-10-15T01:42:16.339478Z"}, {"name": "execute", "started_at": "2022-10-15T01:42:16.340290Z", "completed_at": "2022-10-15T01:42:17.518721Z"}], "thread_id": "Thread-2", "execution_time": 1.5398237705230713, "adapter_response": {"_message": "SUCCESS 1", "code": "SUCCESS", "rows_affected": 1, "query_id": "01a7a266-0000-0a4e-0000-000026c9604d"}, "message": "SUCCESS 1", "failures": null, "unique_id": "model.my_dbt_hero.src_reviews"}], "elapsed_time": 9.12998628616333, "args": {"write_json": true, "use_colors": true, "printer_width": 80, "version_check": true, "partial_parse": true, "static_parser": true, "profiles_dir": "/home/rhavel/.dbt", "send_anonymous_usage_stats": true, "event_buffer_size": 100000, "quiet": false, "no_print": false, "which": "run", "rpc_method": "run", "indirect_selection": "eager"}}